sodom/__init__.py
sodom/__main__.py
sodom/attrs.py
sodom/elements.py
sodom/literals.py
sodom/partial.py
sodom/tags.py
sodom/tests.py
sodom/utils.py
sodom/version.py
sodom-1.1.0.post1.dist-info/METADATA
sodom-1.1.0.post1.dist-info/WHEEL
sodom-1.1.0.post1.dist-info/top_level.txt
sodom-1.1.0.post1.dist-info/RECORD
