Metadata-Version: 2.1
Name: sodom
Version: 1.1.0.post1
Summary: sodom if you like to write HTML in Python.
Author-email: Dmitry Protasov <inbox@protaz.ru>
License: LGPL-3.0-or-newer
Project-URL: Homepage, https://codeberg.org/protasov/sodom
Project-URL: PyPi, https://pypi.org/project/sodom/
Project-URL: Source, https://codeberg.org/protasov/sodom
Keywords: framework,templating,template,html,python,html5
Classifier: Development Status :: 5 - Production/Stable
Classifier: Intended Audience :: Developers
Classifier: License :: OSI Approved :: GNU Lesser General Public License v3 or later (LGPLv3+)
Classifier: Operating System :: OS Independent
Classifier: Programming Language :: Python
Classifier: Programming Language :: Python :: 3.12
Classifier: Programming Language :: Python :: 3.13
Classifier: Topic :: Internet :: WWW/HTTP :: Dynamic Content
Classifier: Topic :: Software Development :: Libraries :: Python Modules
Classifier: Topic :: Text Processing :: Markup :: HTML
Classifier: Framework :: aiohttp
Classifier: Framework :: Flask
Requires-Python: >=3.12
Provides-Extra: cli
Requires-Dist: typer ==0.9.0 ; extra == 'cli'
Requires-Dist: loguru ==0.7.2 ; extra == 'cli'
Requires-Dist: lxml ==4.9.3 ; extra == 'cli'
